mygtu/__init__.py
mygtu/dl.py
mygtu/gtu.py
mygtu/database/subject_code.json
mygtu/utils/__init__.py
mygtu/utils/constants.py
mygtu/utils/profile.py
mygtu/utils/time.py
mygtu/utils/year_list.py
mygtu-0.1.5.dist-info/LICENSE
mygtu-0.1.5.dist-info/METADATA
mygtu-0.1.5.dist-info/WHEEL
mygtu-0.1.5.dist-info/top_level.txt
mygtu-0.1.5.dist-info/RECORD
