Metadata-Version: 2.1
Name: mygtu
Version: 0.1.5
Summary: pyhton interaction with gtu website.
Home-page: https://github.com/mygtu/mygtu
Author: Dhruv Maaniya (@midnightmadwalk)
Author-email: midnightmadwalk@gmail.com
License: MIT
Platform: UNKNOWN
Classifier: Programming Language :: Python :: 3
Classifier: License :: OSI Approved :: MIT License
Classifier: Operating System :: OS Independent
Requires-Python: >=3.6
Requires-Dist: datetime
Requires-Dist: pytz
Requires-Dist: ujson
Requires-Dist: aiofiles
Requires-Dist: aiohttp
Requires-Dist: tqdm
